pydfs/__init__.py
pydfs/__main__.py
pydfs/arg_parse.py
pydfs/cmd_dfs.py
pydfs/cmd_init.py
pydfs/logger.py
pydfs/master_app.py
pydfs/slave_app.py
pydfs/utils.py
dfspy-0.1.0.dist-info/LICENSE
dfspy-0.1.0.dist-info/METADATA
dfspy-0.1.0.dist-info/WHEEL
dfspy-0.1.0.dist-info/entry_points.txt
dfspy-0.1.0.dist-info/top_level.txt
dfspy-0.1.0.dist-info/RECORD
