Metadata-Version: 2.1
Name: dfspy
Version: 0.1.0
Summary: Distributed File System written in Python
Home-page: https://github.com/silkway-ai/pydfs
Author: Dani El-Ayyass, Artem Fomin
Author-email: dayyass@yandex.ru, artfom02@gmail.com
License: UNKNOWN
Keywords: python,distributed-systems,hadoop,filesystem,hdfs,mapreduce
Platform: UNKNOWN
Requires-Dist: flask (==2.1.2)
Requires-Dist: flask-restful (==0.3.9)
Requires-Dist: flask-sqlalchemy (==2.5.1)
Requires-Dist: requests (==2.28.1)
